roboself/__init__.py
roboself/actions.py
roboself/chat.py
roboself/cli/__init__.py
roboself/cli/__main__.py
roboself/cli/cli.py
roboself/cli/commands/__init__.py
roboself/cli/commands/init.py
roboself/cli/commands/run.py
roboself/cli/template/skill/actions.py
roboself/cli/template/skill/nlg/utterances.md
roboself/cli/template/skill/nlu/intents.md
roboself/cli/template/skill/nlu/objects.md
roboself/cli/template/skill/nlu/queries.md
roboself/cli/template/skill/schema.yml
roboself/client.py
roboself/config.py
roboself/context.py
roboself/graph.py
roboself/runtime.py
roboself/serialize.py
roboself/types.py
roboself-0.1.1.dist-info/LICENSE
roboself-0.1.1.dist-info/WHEEL
roboself-0.1.1.dist-info/METADATA
roboself-0.1.1.dist-info/RECORD
