Metadata-Version: 2.1
Name: roboself
Version: 0.1.1
Summary: The roboself python client.
Author: Razvan Dinu
Author-email: razvan@roboself.com
Requires-Python: >=3.6,<4.0
Classifier: Programming Language :: Python :: 3
Classifier: Programming Language :: Python :: 3.6
Classifier: Programming Language :: Python :: 3.7
Classifier: Programming Language :: Python :: 3.8
Requires-Dist: click (>=7.1.2,<8.0.0)
Requires-Dist: python-socketio[client] (>=4.6.0,<5.0.0)
Requires-Dist: pyyaml (>=5.3.1,<6.0.0)
Requires-Dist: redis (>=3.5.3,<4.0.0)
Requires-Dist: requests (>=2.24.0,<3.0.0)
